README
setup.py
src/django_trash.egg-info/PKG-INFO
src/django_trash.egg-info/SOURCES.txt
src/django_trash.egg-info/dependency_links.txt
src/django_trash.egg-info/requires.txt
src/django_trash.egg-info/top_level.txt
src/trash/__init__.py
src/trash/models.py
src/trash/tests.py
src/trash/testsettings.py
src/trash/urls.py
src/trash/views.py