Metadata-Version: 1.0
Name: django-trash
Version: 1.0
Summary: DB trash, app for django
Home-page: UNKNOWN
Author: Kiel Labian
Author-email: UNKNOWN
License: BSD
Platform: UNKNOWN
